azurefunctions/__init__.py
azurefunctions/agents/__init__.py
azurefunctions/agents/agents.py
azurefunctions/agents/core.py
azurefunctions/agents/runner.py
azurefunctions/agents/types.py
azurefunctions/agents/a2a/__init__.py
azurefunctions/agents/a2a/client.py
azurefunctions/agents/a2a/manager.py
azurefunctions/agents/a2a/task_manager.py
azurefunctions/agents/mcp/__init__.py
azurefunctions/agents/mcp/result_formatter.py
azurefunctions/agents/mcp/server.py
azurefunctions/agents/mcp/util.py
azurefunctions/agents/model_providers/__init__.py
azurefunctions/agents/model_providers/anthropic_provider.py
azurefunctions/agents/model_providers/azure_openai_provider.py
azurefunctions/agents/model_providers/base.py
azurefunctions/agents/model_providers/client.py
azurefunctions/agents/model_providers/google_provider.py
azurefunctions/agents/model_providers/openai_provider.py
azurefunctions/agents/tools/__init__.py
azurefunctions/agents/tools/function_tools.py
azurefunctions/agents/tools/mcp_tools.py
azurefunctions/agents/tools/tool_registry.py
azurefunctions_agent_framework-0.0.1a2.dist-info/METADATA
azurefunctions_agent_framework-0.0.1a2.dist-info/WHEEL
azurefunctions_agent_framework-0.0.1a2.dist-info/top_level.txt
azurefunctions_agent_framework-0.0.1a2.dist-info/RECORD
