Metadata-Version: 2.4
Name: azurefunctions-agent-framework
Version: 0.0.1a2
Summary: Base Python worker extension for Azure Functions.
Author-email: "Azure Functions team at Microsoft Corp." <azurefunctions@microsoft.com>
License-Expression: MIT
Classifier: Intended Audience :: Developers
Classifier: Programming Language :: Python :: 3
Classifier: Programming Language :: Python :: 3.10
Classifier: Programming Language :: Python :: 3.11
Classifier: Programming Language :: Python :: 3.12
Classifier: Programming Language :: Python :: 3.13
Classifier: Operating System :: Microsoft :: Windows
Classifier: Operating System :: POSIX
Classifier: Operating System :: MacOS :: MacOS X
Classifier: Environment :: Web Environment
Classifier: Development Status :: 3 - Alpha
Requires-Python: >=3.10
Requires-Dist: azure-functions
Requires-Dist: mcp
Requires-Dist: typing_extensions
Requires-Dist: pydantic
Requires-Dist: httpx
Requires-Dist: aiohttp
Requires-Dist: a2a-sdk
Provides-Extra: openai
Requires-Dist: openai>=1.0.0; extra == "openai"
Provides-Extra: anthropic
Requires-Dist: anthropic>=0.20.0; extra == "anthropic"
Provides-Extra: google
Requires-Dist: google-genai>=0.3.0; extra == "google"
Provides-Extra: ollama
Requires-Dist: ollama>=0.1.0; extra == "ollama"
Provides-Extra: azure-ai
Requires-Dist: azure-ai-inference; extra == "azure-ai"
Provides-Extra: azure
Requires-Dist: azure-ai-projects; extra == "azure"
Requires-Dist: azure-identity; extra == "azure"
Requires-Dist: azure-keyvault-secrets; extra == "azure"
Provides-Extra: all
Requires-Dist: openai>=1.0.0; extra == "all"
Requires-Dist: anthropic>=0.20.0; extra == "all"
Requires-Dist: google-genai>=0.3.0; extra == "all"
Requires-Dist: ollama>=0.1.0; extra == "all"
Requires-Dist: azure-ai-inference; extra == "all"
Requires-Dist: azure-ai-projects; extra == "all"
Requires-Dist: azure-identity; extra == "all"
Requires-Dist: azure-keyvault-secrets; extra == "all"
Provides-Extra: dev
Requires-Dist: isort; extra == "dev"
Requires-Dist: black; extra == "dev"
Requires-Dist: pytest; extra == "dev"
Requires-Dist: pytest-asyncio; extra == "dev"
Requires-Dist: mypy; extra == "dev"
